README.md
setup.py
antho_utils.egg-info/PKG-INFO
antho_utils.egg-info/SOURCES.txt
antho_utils.egg-info/dependency_links.txt
antho_utils.egg-info/requires.txt
antho_utils.egg-info/top_level.txt
pyutils/__init__.py
pyutils/__version__.py
pyutils/color.py
pyutils/configFile.py
pyutils/feedback.py
pyutils/logger.py
pyutils/progress.py